verilog_study/test.v
module majority_voter(
    input wire a,
    input wire b,
    input wire c,
    output wire y
);
    assign y = (a & b)|(a & c)|(b & c);
endmodule



module adder4(
    input [3:0] a,
    input [3:0] b,
    output [4:0] sum
);
    wire [3:0] carry;
    
    assign sum[0] = a[0] ^ b[0];
    assign carry[0] = a[0] & b[0];
    
    assign sum[1] = a[1] ^ b[1] ^ carry[0];
    assign carry[1] = (a[1] & b[1]) | (b[1] & carry[0]) | (a[1] & carry[0]);
    
    assign sum[2] = a[2] ^ b[2] ^ carry[1];
    assign carry[2] = (a[2] & b[2]) | (b[2] & carry[1]) | (a[2] & carry[1]);
    
    assign sum[3] = a[3] ^ b[3] ^ carry[2];
    assign sum[4] = (a[3] & b[3]) | (b[3] & carry[2]) | (a[3] & carry[2]); // 进位作为sum的最高位
endmodule




module mux8to1(
    input [7:0] data_in,
    input [2:0] sel,
    output wire data_out
);
    assign data_out = (sel == 3'b000) ? data_in[0] :
                 (sel == 3'b001) ? data_in[1] :
                 (sel == 3'b010) ? data_in[2] :
                 (sel == 3'b011) ? data_in[3] :
                 (sel == 3'b100) ? data_in[4] :
                 (sel == 3'b101) ? data_in[5] :
                 (sel == 3'b110) ? data_in[6] :
                 (sel == 3'b111) ? data_in[7] : 1'b0;
endmodule


module x(
    input wire A,B,C,
    output wire F
);
    assign F = A & C;
endmodule

/*
A	B	C	F
0	0	0	0
0	0	1	0
0	1	0	0
0	1	1	0
1	0	0	0
1	0	1	1
1	1	0	0
1	1	1	1
*/

verilog_study/adder4_tb.v
`timescale 1ns/1ps

module adder4_tb;
    reg [3:0] a, b;
    wire [4:0] sum;
    
    adder4 uut (.a(a), .b(b), .sum(sum));

    integer i,j;
    initial begin
        $monitor("Time = %0t | a = %0d, b = %0d, sum = %0d", 
                 $time, a, b, sum);

        // 遍历所有输入组合
        for (i = 0; i < 16; i = i + 1) begin
            for (j = 0; j < 16; j = j + 1) begin
                a = i;
                b = j;
                #10;
            end
        end
        $finish;
    end

    // 生成波形文件
    initial begin
        $dumpfile("adder4.vcd");
        $dumpvars(0, adder4_tb);
    end
endmodule

verilog_study/adder4.vcd
$date
	Wed Apr 30 10:16:39 2025
$end
$version
	Icarus Verilog
$end
$timescale
	1ps
$end
$scope module adder4_tb $end
$var wire 5 ! sum [4:0] $end
$var reg 4 " a [3:0] $end
$var reg 4 # b [3:0] $end
$var integer 32 $ i [31:0] $end
$var integer 32 % j [31:0] $end
$scope module uut $end
$var wire 4 & a [3:0] $end
$var wire 4 ' b [3:0] $end
$var wire 5 ( sum [4:0] $end
$var wire 4 ) carry [3:0] $end
$upscope $end
$upscope $end
$enddefinitions $end
$comment Show the parameter values. $end
$dumpall
$end
#0
$dumpvars
bz000 )
b0 (
b0 '
b0 &
b0 %
b0 $
b0 #
b0 "
b0 !
$end
#10000
b1 !
b1 (
b1 #
b1 '
b1 %
#20000
b10 !
b10 (
b10 #
b10 '
b10 %
#30000
b11 !
b11 (
b11 #
b11 '
b11 %
#40000
b100 !
b100 (
b100 #
b100 '
b100 %
#50000
b101 !
b101 (
b101 #
b101 '
b101 %
#60000
b110 !
b110 (
b110 #
b110 '
b110 %
#70000
b111 !
b111 (
b111 #
b111 '
b111 %
#80000
b1000 !
b1000 (
b1000 #
b1000 '
b1000 %
#90000
b1001 !
b1001 (
b1001 #
b1001 '
b1001 %
#100000
b1010 !
b1010 (
b1010 #
b1010 '
b1010 %
#110000
b1011 !
b1011 (
b1011 #
b1011 '
b1011 %
#120000
b1100 !
b1100 (
b1100 #
b1100 '
b1100 %
#130000
b1101 !
b1101 (
b1101 #
b1101 '
b1101 %
#140000
b1110 !
b1110 (
b1110 #
b1110 '
b1110 %
#150000
b1111 !
b1111 (
b1111 #
b1111 '
b1111 %
#160000
b1 !
b1 (
b0 #
b0 '
b1 "
b1 &
b1 $
b0 %
#170000
b10 !
b10 (
bz001 )
b1 #
b1 '
b1 %
#180000
b11 !
b11 (
bz000 )
b10 #
b10 '
b10 %
#190000
b100 !
b100 (
bz011 )
b11 #
b11 '
b11 %
#200000
b101 !
b101 (
bz000 )
b100 #
b100 '
b100 %
#210000
b110 !
b110 (
bz001 )
b101 #
b101 '
b101 %
#220000
b111 !
b111 (
bz000 )
b110 #
b110 '
b110 %
#230000
b1000 !
b1000 (
bz111 )
b111 #
b111 '
b111 %
#240000
b1001 !
b1001 (
bz000 )
b1000 #
b1000 '
b1000 %
#250000
b1010 !
b1010 (
bz001 )
b1001 #
b1001 '
b1001 %
#260000
b1011 !
b1011 (
bz000 )
b1010 #
b1010 '
b1010 %
#270000
b1100 !
b1100 (
bz011 )
b1011 #
b1011 '
b1011 %
#280000
b1101 !
b1101 (
bz000 )
b1100 #
b1100 '
b1100 %
#290000
b1110 !
b1110 (
bz001 )
b1101 #
b1101 '
b1101 %
#300000
b1111 !
b1111 (
bz000 )
b1110 #
b1110 '
b1110 %
#310000
b10000 !
b10000 (
bz111 )
b1111 #
b1111 '
b1111 %
#320000
b10 !
b10 (
bz000 )
b0 #
b0 '
b10 "
b10 &
b10 $
b0 %
#330000
b11 !
b11 (
b1 #
b1 '
b1 %
#340000
bz010 )
b100 !
b100 (
b10 #
b10 '
b10 %
#350000
b101 !
b101 (
b11 #
b11 '
b11 %
#360000
bz000 )
b110 !
b110 (
b100 #
b100 '
b100 %
#370000
b111 !
b111 (
b101 #
b101 '
b101 %
#380000
bz110 )
b1000 !
b1000 (
b110 #
b110 '
b110 %
#390000
b1001 !
b1001 (
b111 #
b111 '
b111 %
#400000
bz000 )
b1010 !
b1010 (
b1000 #
b1000 '
b1000 %
#410000
b1011 !
b1011 (
b1001 #
b1001 '
b1001 %
#420000
bz010 )
b1100 !
b1100 (
b1010 #
b1010 '
b1010 %
#430000
b1101 !
b1101 (
b1011 #
b1011 '
b1011 %
#440000
bz000 )
b1110 !
b1110 (
b1100 #
b1100 '
b1100 %
#450000
b1111 !
b1111 (
b1101 #
b1101 '
b1101 %
#460000
bz110 )
b10000 !
b10000 (
b1110 #
b1110 '
b1110 %
#470000
b10001 !
b10001 (
b1111 #
b1111 '
b1111 %
#480000
bz000 )
b11 !
b11 (
b0 #
b0 '
b11 "
b11 &
b11 $
b0 %
#490000
b100 !
b100 (
bz011 )
b1 #
b1 '
b1 %
#500000
b101 !
b101 (
bz010 )
b10 #
b10 '
b10 %
#510000
b110 !
b110 (
bz011 )
b11 #
b11 '
b11 %
#520000
b111 !
b111 (
bz000 )
b100 #
b100 '
b100 %
#530000
b1000 !
b1000 (
bz111 )
b101 #
b101 '
b101 %
#540000
b1001 !
b1001 (
bz110 )
b110 #
b110 '
b110 %
#550000
b1010 !
b1010 (
bz111 )
b111 #
b111 '
b111 %
#560000
b1011 !
b1011 (
bz000 )
b1000 #
b1000 '
b1000 %
#570000
b1100 !
b1100 (
bz011 )
b1001 #
b1001 '
b1001 %
#580000
b1101 !
b1101 (
bz010 )
b1010 #
b1010 '
b1010 %
#590000
b1110 !
b1110 (
bz011 )
b1011 #
b1011 '
b1011 %
#600000
b1111 !
b1111 (
bz000 )
b1100 #
b1100 '
b1100 %
#610000
b10000 !
b10000 (
bz111 )
b1101 #
b1101 '
b1101 %
#620000
b10001 !
b10001 (
bz110 )
b1110 #
b1110 '
b1110 %
#630000
b10010 !
b10010 (
bz111 )
b1111 #
b1111 '
b1111 %
#640000
b100 !
b100 (
bz000 )
b0 #
b0 '
b100 "
b100 &
b100 $
b0 %
#650000
b101 !
b101 (
b1 #
b1 '
b1 %
#660000
b110 !
b110 (
b10 #
b10 '
b10 %
#670000
b111 !
b111 (
b11 #
b11 '
b11 %
#680000
bz100 )
b1000 !
b1000 (
b100 #
b100 '
b100 %
#690000
b1001 !
b1001 (
b101 #
b101 '
b101 %
#700000
b1010 !
b1010 (
b110 #
b110 '
b110 %
#710000
b1011 !
b1011 (
b111 #
b111 '
b111 %
#720000
bz000 )
b1100 !
b1100 (
b1000 #
b1000 '
b1000 %
#730000
b1101 !
b1101 (
b1001 #
b1001 '
b1001 %
#740000
b1110 !
b1110 (
b1010 #
b1010 '
b1010 %
#750000
b1111 !
b1111 (
b1011 #
b1011 '
b1011 %
#760000
bz100 )
b10000 !
b10000 (
b1100 #
b1100 '
b1100 %
#770000
b10001 !
b10001 (
b1101 #
b1101 '
b1101 %
#780000
b10010 !
b10010 (
b1110 #
b1110 '
b1110 %
#790000
b10011 !
b10011 (
b1111 #
b1111 '
b1111 %
#800000
bz000 )
b101 !
b101 (
b0 #
b0 '
b101 "
b101 &
b101 $
b0 %
#810000
b110 !
b110 (
bz001 )
b1 #
b1 '
b1 %
#820000
b111 !
b111 (
bz000 )
b10 #
b10 '
b10 %
#830000
b1000 !
b1000 (
bz111 )
b11 #
b11 '
b11 %
#840000
b1001 !
b1001 (
bz100 )
b100 #
b100 '
b100 %
#850000
b1010 !
b1010 (
bz101 )
b101 #
b101 '
b101 %
#860000
b1011 !
b1011 (
bz100 )
b110 #
b110 '
b110 %
#870000
b1100 !
b1100 (
bz111 )
b111 #
b111 '
b111 %
#880000
b1101 !
b1101 (
bz000 )
b1000 #
b1000 '
b1000 %
#890000
b1110 !
b1110 (
bz001 )
b1001 #
b1001 '
b1001 %
#900000
b1111 !
b1111 (
bz000 )
b1010 #
b1010 '
b1010 %
#910000
b10000 !
b10000 (
bz111 )
b1011 #
b1011 '
b1011 %
#920000
b10001 !
b10001 (
bz100 )
b1100 #
b1100 '
b1100 %
#930000
b10010 !
b10010 (
bz101 )
b1101 #
b1101 '
b1101 %
#940000
b10011 !
b10011 (
bz100 )
b1110 #
b1110 '
b1110 %
#950000
b10100 !
b10100 (
bz111 )
b1111 #
b1111 '
b1111 %
#960000
b110 !
b110 (
bz000 )
b0 #
b0 '
b110 "
b110 &
b110 $
b0 %
#970000
b111 !
b111 (
b1 #
b1 '
b1 %
#980000
bz110 )
b1000 !
b1000 (
b10 #
b10 '
b10 %
#990000
b1001 !
b1001 (
b11 #
b11 '
b11 %
#1000000
bz100 )
b1010 !
b1010 (
b100 #
b100 '
b100 %
#1010000
b1011 !
b1011 (
b101 #
b101 '
b101 %
#1020000
bz110 )
b1100 !
b1100 (
b110 #
b110 '
b110 %
#1030000
b1101 !
b1101 (
b111 #
b111 '
b111 %
#1040000
bz000 )
b1110 !
b1110 (
b1000 #
b1000 '
b1000 %
#1050000
b1111 !
b1111 (
b1001 #
b1001 '
b1001 %
#1060000
bz110 )
b10000 !
b10000 (
b1010 #
b1010 '
b1010 %
#1070000
b10001 !
b10001 (
b1011 #
b1011 '
b1011 %
#1080000
bz100 )
b10010 !
b10010 (
b1100 #
b1100 '
b1100 %
#1090000
b10011 !
b10011 (
b1101 #
b1101 '
b1101 %
#1100000
bz110 )
b10100 !
b10100 (
b1110 #
b1110 '
b1110 %
#1110000
b10101 !
b10101 (
b1111 #
b1111 '
b1111 %
#1120000
bz000 )
b111 !
b111 (
b0 #
b0 '
b111 "
b111 &
b111 $
b0 %
#1130000
b1000 !
b1000 (
bz111 )
b1 #
b1 '
b1 %
#1140000
b1001 !
b1001 (
bz110 )
b10 #
b10 '
b10 %
#1150000
b1010 !
b1010 (
bz111 )
b11 #
b11 '
b11 %
#1160000
b1011 !
b1011 (
bz100 )
b100 #
b100 '
b100 %
#1170000
b1100 !
b1100 (
bz111 )
b101 #
b101 '
b101 %
#1180000
b1101 !
b1101 (
bz110 )
b110 #
b110 '
b110 %
#1190000
b1110 !
b1110 (
bz111 )
b111 #
b111 '
b111 %
#1200000
b1111 !
b1111 (
bz000 )
b1000 #
b1000 '
b1000 %
#1210000
b10000 !
b10000 (
bz111 )
b1001 #
b1001 '
b1001 %
#1220000
b10001 !
b10001 (
bz110 )
b1010 #
b1010 '
b1010 %
#1230000
b10010 !
b10010 (
bz111 )
b1011 #
b1011 '
b1011 %
#1240000
b10011 !
b10011 (
bz100 )
b1100 #
b1100 '
b1100 %
#1250000
b10100 !
b10100 (
bz111 )
b1101 #
b1101 '
b1101 %
#1260000
b10101 !
b10101 (
bz110 )
b1110 #
b1110 '
b1110 %
#1270000
b10110 !
b10110 (
bz111 )
b1111 #
b1111 '
b1111 %
#1280000
b1000 !
b1000 (
bz000 )
b0 #
b0 '
b1000 "
b1000 &
b1000 $
b0 %
#1290000
b1001 !
b1001 (
b1 #
b1 '
b1 %
#1300000
b1010 !
b1010 (
b10 #
b10 '
b10 %
#1310000
b1011 !
b1011 (
b11 #
b11 '
b11 %
#1320000
b1100 !
b1100 (
b100 #
b100 '
b100 %
#1330000
b1101 !
b1101 (
b101 #
b101 '
b101 %
#1340000
b1110 !
b1110 (
b110 #
b110 '
b110 %
#1350000
b1111 !
b1111 (
b111 #
b111 '
b111 %
#1360000
b10000 !
b10000 (
b1000 #
b1000 '
b1000 %
#1370000
b10001 !
b10001 (
b1001 #
b1001 '
b1001 %
#1380000
b10010 !
b10010 (
b1010 #
b1010 '
b1010 %
#1390000
b10011 !
b10011 (
b1011 #
b1011 '
b1011 %
#1400000
b10100 !
b10100 (
b1100 #
b1100 '
b1100 %
#1410000
b10101 !
b10101 (
b1101 #
b1101 '
b1101 %
#1420000
b10110 !
b10110 (
b1110 #
b1110 '
b1110 %
#1430000
b10111 !
b10111 (
b1111 #
b1111 '
b1111 %
#1440000
b1001 !
b1001 (
b0 #
b0 '
b1001 "
b1001 &
b1001 $
b0 %
#1450000
b1010 !
b1010 (
bz001 )
b1 #
b1 '
b1 %
#1460000
b1011 !
b1011 (
bz000 )
b10 #
b10 '
b10 %
#1470000
b1100 !
b1100 (
bz011 )
b11 #
b11 '
b11 %
#1480000
b1101 !
b1101 (
bz000 )
b100 #
b100 '
b100 %
#1490000
b1110 !
b1110 (
bz001 )
b101 #
b101 '
b101 %
#1500000
b1111 !
b1111 (
bz000 )
b110 #
b110 '
b110 %
#1510000
b10000 !
b10000 (
bz111 )
b111 #
b111 '
b111 %
#1520000
b10001 !
b10001 (
bz000 )
b1000 #
b1000 '
b1000 %
#1530000
b10010 !
b10010 (
bz001 )
b1001 #
b1001 '
b1001 %
#1540000
b10011 !
b10011 (
bz000 )
b1010 #
b1010 '
b1010 %
#1550000
b10100 !
b10100 (
bz011 )
b1011 #
b1011 '
b1011 %
#1560000
b10101 !
b10101 (
bz000 )
b1100 #
b1100 '
b1100 %
#1570000
b10110 !
b10110 (
bz001 )
b1101 #
b1101 '
b1101 %
#1580000
b10111 !
b10111 (
bz000 )
b1110 #
b1110 '
b1110 %
#1590000
b11000 !
b11000 (
bz111 )
b1111 #
b1111 '
b1111 %
#1600000
b1010 !
b1010 (
bz000 )
b0 #
b0 '
b1010 "
b1010 &
b1010 $
b0 %
#1610000
b1011 !
b1011 (
b1 #
b1 '
b1 %
#1620000
bz010 )
b1100 !
b1100 (
b10 #
b10 '
b10 %
#1630000
b1101 !
b1101 (
b11 #
b11 '
b11 %
#1640000
bz000 )
b1110 !
b1110 (
b100 #
b100 '
b100 %
#1650000
b1111 !
b1111 (
b101 #
b101 '
b101 %
#1660000
bz110 )
b10000 !
b10000 (
b110 #
b110 '
b110 %
#1670000
b10001 !
b10001 (
b111 #
b111 '
b111 %
#1680000
bz000 )
b10010 !
b10010 (
b1000 #
b1000 '
b1000 %
#1690000
b10011 !
b10011 (
b1001 #
b1001 '
b1001 %
#1700000
bz010 )
b10100 !
b10100 (
b1010 #
b1010 '
b1010 %
#1710000
b10101 !
b10101 (
b1011 #
b1011 '
b1011 %
#1720000
bz000 )
b10110 !
b10110 (
b1100 #
b1100 '
b1100 %
#1730000
b10111 !
b10111 (
b1101 #
b1101 '
b1101 %
#1740000
bz110 )
b11000 !
b11000 (
b1110 #
b1110 '
b1110 %
#1750000
b11001 !
b11001 (
b1111 #
b1111 '
b1111 %
#1760000
bz000 )
b1011 !
b1011 (
b0 #
b0 '
b1011 "
b1011 &
b1011 $
b0 %
#1770000
b1100 !
b1100 (
bz011 )
b1 #
b1 '
b1 %
#1780000
b1101 !
b1101 (
bz010 )
b10 #
b10 '
b10 %
#1790000
b1110 !
b1110 (
bz011 )
b11 #
b11 '
b11 %
#1800000
b1111 !
b1111 (
bz000 )
b100 #
b100 '
b100 %
#1810000
b10000 !
b10000 (
bz111 )
b101 #
b101 '
b101 %
#1820000
b10001 !
b10001 (
bz110 )
b110 #
b110 '
b110 %
#1830000
b10010 !
b10010 (
bz111 )
b111 #
b111 '
b111 %
#1840000
b10011 !
b10011 (
bz000 )
b1000 #
b1000 '
b1000 %
#1850000
b10100 !
b10100 (
bz011 )
b1001 #
b1001 '
b1001 %
#1860000
b10101 !
b10101 (
bz010 )
b1010 #
b1010 '
b1010 %
#1870000
b10110 !
b10110 (
bz011 )
b1011 #
b1011 '
b1011 %
#1880000
b10111 !
b10111 (
bz000 )
b1100 #
b1100 '
b1100 %
#1890000
b11000 !
b11000 (
bz111 )
b1101 #
b1101 '
b1101 %
#1900000
b11001 !
b11001 (
bz110 )
b1110 #
b1110 '
b1110 %
#1910000
b11010 !
b11010 (
bz111 )
b1111 #
b1111 '
b1111 %
#1920000
b1100 !
b1100 (
bz000 )
b0 #
b0 '
b1100 "
b1100 &
b1100 $
b0 %
#1930000
b1101 !
b1101 (
b1 #
b1 '
b1 %
#1940000
b1110 !
b1110 (
b10 #
b10 '
b10 %
#1950000
b1111 !
b1111 (
b11 #
b11 '
b11 %
#1960000
bz100 )
b10000 !
b10000 (
b100 #
b100 '
b100 %
#1970000
b10001 !
b10001 (
b101 #
b101 '
b101 %
#1980000
b10010 !
b10010 (
b110 #
b110 '
b110 %
#1990000
b10011 !
b10011 (
b111 #
b111 '
b111 %
#2000000
bz000 )
b10100 !
b10100 (
b1000 #
b1000 '
b1000 %
#2010000
b10101 !
b10101 (
b1001 #
b1001 '
b1001 %
#2020000
b10110 !
b10110 (
b1010 #
b1010 '
b1010 %
#2030000
b10111 !
b10111 (
b1011 #
b1011 '
b1011 %
#2040000
bz100 )
b11000 !
b11000 (
b1100 #
b1100 '
b1100 %
#2050000
b11001 !
b11001 (
b1101 #
b1101 '
b1101 %
#2060000
b11010 !
b11010 (
b1110 #
b1110 '
b1110 %
#2070000
b11011 !
b11011 (
b1111 #
b1111 '
b1111 %
#2080000
bz000 )
b1101 !
b1101 (
b0 #
b0 '
b1101 "
b1101 &
b1101 $
b0 %
#2090000
b1110 !
b1110 (
bz001 )
b1 #
b1 '
b1 %
#2100000
b1111 !
b1111 (
bz000 )
b10 #
b10 '
b10 %
#2110000
b10000 !
b10000 (
bz111 )
b11 #
b11 '
b11 %
#2120000
b10001 !
b10001 (
bz100 )
b100 #
b100 '
b100 %
#2130000
b10010 !
b10010 (
bz101 )
b101 #
b101 '
b101 %
#2140000
b10011 !
b10011 (
bz100 )
b110 #
b110 '
b110 %
#2150000
b10100 !
b10100 (
bz111 )
b111 #
b111 '
b111 %
#2160000
b10101 !
b10101 (
bz000 )
b1000 #
b1000 '
b1000 %
#2170000
b10110 !
b10110 (
bz001 )
b1001 #
b1001 '
b1001 %
#2180000
b10111 !
b10111 (
bz000 )
b1010 #
b1010 '
b1010 %
#2190000
b11000 !
b11000 (
bz111 )
b1011 #
b1011 '
b1011 %
#2200000
b11001 !
b11001 (
bz100 )
b1100 #
b1100 '
b1100 %
#2210000
b11010 !
b11010 (
bz101 )
b1101 #
b1101 '
b1101 %
#2220000
b11011 !
b11011 (
bz100 )
b1110 #
b1110 '
b1110 %
#2230000
b11100 !
b11100 (
bz111 )
b1111 #
b1111 '
b1111 %
#2240000
b1110 !
b1110 (
bz000 )
b0 #
b0 '
b1110 "
b1110 &
b1110 $
b0 %
#2250000
b1111 !
b1111 (
b1 #
b1 '
b1 %
#2260000
bz110 )
b10000 !
b10000 (
b10 #
b10 '
b10 %
#2270000
b10001 !
b10001 (
b11 #
b11 '
b11 %
#2280000
bz100 )
b10010 !
b10010 (
b100 #
b100 '
b100 %
#2290000
b10011 !
b10011 (
b101 #
b101 '
b101 %
#2300000
bz110 )
b10100 !
b10100 (
b110 #
b110 '
b110 %
#2310000
b10101 !
b10101 (
b111 #
b111 '
b111 %
#2320000
bz000 )
b10110 !
b10110 (
b1000 #
b1000 '
b1000 %
#2330000
b10111 !
b10111 (
b1001 #
b1001 '
b1001 %
#2340000
bz110 )
b11000 !
b11000 (
b1010 #
b1010 '
b1010 %
#2350000
b11001 !
b11001 (
b1011 #
b1011 '
b1011 %
#2360000
bz100 )
b11010 !
b11010 (
b1100 #
b1100 '
b1100 %
#2370000
b11011 !
b11011 (
b1101 #
b1101 '
b1101 %
#2380000
bz110 )
b11100 !
b11100 (
b1110 #
b1110 '
b1110 %
#2390000
b11101 !
b11101 (
b1111 #
b1111 '
b1111 %
#2400000
bz000 )
b1111 !
b1111 (
b0 #
b0 '
b1111 "
b1111 &
b1111 $
b0 %
#2410000
b10000 !
b10000 (
bz111 )
b1 #
b1 '
b1 %
#2420000
b10001 !
b10001 (
bz110 )
b10 #
b10 '
b10 %
#2430000
b10010 !
b10010 (
bz111 )
b11 #
b11 '
b11 %
#2440000
b10011 !
b10011 (
bz100 )
b100 #
b100 '
b100 %
#2450000
b10100 !
b10100 (
bz111 )
b101 #
b101 '
b101 %
#2460000
b10101 !
b10101 (
bz110 )
b110 #
b110 '
b110 %
#2470000
b10110 !
b10110 (
bz111 )
b111 #
b111 '
b111 %
#2480000
b10111 !
b10111 (
bz000 )
b1000 #
b1000 '
b1000 %
#2490000
b11000 !
b11000 (
bz111 )
b1001 #
b1001 '
b1001 %
#2500000
b11001 !
b11001 (
bz110 )
b1010 #
b1010 '
b1010 %
#2510000
b11010 !
b11010 (
bz111 )
b1011 #
b1011 '
b1011 %
#2520000
b11011 !
b11011 (
bz100 )
b1100 #
b1100 '
b1100 %
#2530000
b11100 !
b11100 (
bz111 )
b1101 #
b1101 '
b1101 %
#2540000
b11101 !
b11101 (
bz110 )
b1110 #
b1110 '
b1110 %
#2550000
b11110 !
b11110 (
bz111 )
b1111 #
b1111 '
b1111 %
#2560000
b10000 $
b10000 %
