verilog_study/test.v
module majority_voter(
    input wire a,
    input wire b,
    input wire c,
    output wire y
);
    assign y = (a & b)|(a & c)|(b & c);
endmodule



module adder4(
    input [3:0] a,
    input [3:0] b,
    output [4:0] sum
);
    wire [3:0] carry;
    
    assign sum[0] = a[0] ^ b[0];
    assign carry[0] = a[0] & b[0];
    
    assign sum[1] = a[1] ^ b[1] ^ carry[0];
    assign carry[1] = (a[1] & b[1]) | (b[1] & carry[0]) | (a[1] & carry[0]);
    
    assign sum[2] = a[2] ^ b[2] ^ carry[1];
    assign carry[2] = (a[2] & b[2]) | (b[2] & carry[1]) | (a[2] & carry[1]);
    
    assign sum[3] = a[3] ^ b[3] ^ carry[2];
    assign sum[4] = (a[3] & b[3]) | (b[3] & carry[2]) | (a[3] & carry[2]); // 进位作为sum的最高位
endmodule




module mux8to1(
    input [7:0] data_in,
    input [2:0] sel,
    output wire data_out
);
    assign data_out = (sel == 3'b000) ? data_in[0] :
                 (sel == 3'b001) ? data_in[1] :
                 (sel == 3'b010) ? data_in[2] :
                 (sel == 3'b011) ? data_in[3] :
                 (sel == 3'b100) ? data_in[4] :
                 (sel == 3'b101) ? data_in[5] :
                 (sel == 3'b110) ? data_in[6] :
                 (sel == 3'b111) ? data_in[7] : 1'b0;
endmodule


module x(
    input wire A,B,C,
    output wire F
);
    assign F = A & C;
endmodule

/*
A	B	C	F
0	0	0	0
0	0	1	0
0	1	0	0
0	1	1	0
1	0	0	0
1	0	1	1
1	1	0	0
1	1	1	1
*/

verilog_study/majority_voter_tb.v
`timescale 1ns/1ps

module majority_voter_tb;
    reg a, b, c;
    wire y;

    majority_voter uut(
        .a(a),
        .b(b),
        .c(c),
        .y(y)
    );

    initial begin
        $monitor("Time = %0t | a = %b, b = %b, c = %b, y = %b", $time, a, b, c, y);

        a = 0; b = 0; c = 0; #100;
        a = 0; b = 0; c = 1; #100;
        a = 0; b = 1; c = 0; #100;
        a = 0; b = 1; c = 1; #100;
        a = 1; b = 0; c = 0; #100;
        a = 1; b = 0; c = 1; #100;
        a = 1; b = 1; c = 0; #100;
        a = 1; b = 1; c = 1;

    end

initial
begin
    $dumpfile("majority_voter.vcd");
    $dumpvars(0, majority_voter_tb);
end
endmodule

verilog_study/majority_voter.vcd
$date
	Mon Apr 28 15:10:52 2025
$end
$version
	Icarus Verilog
$end
$timescale
	1ps
$end
$scope module majority_voter_tb $end
$var wire 1 ! y $end
$var reg 1 " a $end
$var reg 1 # b $end
$var reg 1 $ c $end
$scope module majority_voter_0 $end
$var wire 1 " a $end
$var wire 1 # b $end
$var wire 1 $ c $end
$var wire 1 ! y $end
$upscope $end
$upscope $end
$enddefinitions $end
$comment Show the parameter values. $end
$dumpall
$end
#0
$dumpvars
0$
0#
0"
0!
$end
#100000
1$
#200000
0$
1#
#300000
1!
1$
#400000
0!
0$
0#
1"
#500000
1!
1$
#600000
0$
1#
#700000
1$
