verilog_study/test.v
module majority_voter(
    input wire a,
    input wire b,
    input wire c,
    output wire y
);
    assign y = (a & b)|(a & c)|(b & c);
endmodule



module adder4(
    input [3:0] a,
    input [3:0] b,
    output [4:0] sum
);
    wire [3:0] carry;
    
    assign sum[0] = a[0] ^ b[0];
    assign carry[0] = a[0] & b[0];
    
    assign sum[1] = a[1] ^ b[1] ^ carry[0];
    assign carry[1] = (a[1] & b[1]) | (b[1] & carry[0]) | (a[1] & carry[0]);
    
    assign sum[2] = a[2] ^ b[2] ^ carry[1];
    assign carry[2] = (a[2] & b[2]) | (b[2] & carry[1]) | (a[2] & carry[1]);
    
    assign sum[3] = a[3] ^ b[3] ^ carry[2];
    assign sum[4] = (a[3] & b[3]) | (b[3] & carry[2]) | (a[3] & carry[2]); // 进位作为sum的最高位
endmodule




module mux8to1(
    input [7:0] data_in,
    input [2:0] sel,
    output wire data_out
);
    assign data_out = (sel == 3'b000) ? data_in[0] :
                 (sel == 3'b001) ? data_in[1] :
                 (sel == 3'b010) ? data_in[2] :
                 (sel == 3'b011) ? data_in[3] :
                 (sel == 3'b100) ? data_in[4] :
                 (sel == 3'b101) ? data_in[5] :
                 (sel == 3'b110) ? data_in[6] :
                 (sel == 3'b111) ? data_in[7] : 1'b0;
endmodule


module x(
    input wire A,B,C,
    output wire F
);
    assign F = A & C;
endmodule

/*
A	B	C	F
0	0	0	0
0	0	1	0
0	1	0	0
0	1	1	0
1	0	0	0
1	0	1	1
1	1	0	0
1	1	1	1
*/

verilog_study/mux8to1_tb.v
`timescale 1ns/1ps

module mux8to1_tb;
    reg [7:0] data_in;
    reg [2:0] sel;
    wire data_out;

    mux8to1 uut (.data_in(data_in),.sel(sel),.data_out(data_out));

    integer count = 0;
    initial begin
        $monitor("Time = %0t | data_in = %0d,sel = %0d,data_out = %0d",
                $time,data_in,sel,data_out);
    data_in = 8'b10011101;
    for(sel = 3'b000;sel <= 3'b111 && count < 8;sel = sel +1)begin
        #10;
        count = count +1;
        end
    $finish;
    end

    initial begin
        $dumpfile("mux8to1.vcd");
        $dumpvars(0,mux8to1_tb);
    end
endmodule

verilog_study/mux8to1.vcd
$date
	Wed Apr 30 10:49:56 2025
$end
$version
	Icarus Verilog
$end
$timescale
	1ps
$end
$scope module mux8to1_tb $end
$var wire 1 ! data_out $end
$var reg 8 " data_in [7:0] $end
$var reg 3 # sel [2:0] $end
$var integer 32 $ count [31:0] $end
$scope module uut $end
$var wire 8 % data_in [7:0] $end
$var wire 3 & sel [2:0] $end
$var wire 1 ! data_out $end
$upscope $end
$upscope $end
$enddefinitions $end
$comment Show the parameter values. $end
$dumpall
$end
#0
$dumpvars
b0 &
b10011101 %
b0 $
b0 #
b10011101 "
1!
$end
#10000
0!
b1 #
b1 &
b1 $
#20000
1!
b10 #
b10 &
b10 $
#30000
b11 #
b11 &
b11 $
#40000
b100 #
b100 &
b100 $
#50000
0!
b101 #
b101 &
b101 $
#60000
b110 #
b110 &
b110 $
#70000
1!
b111 #
b111 &
b111 $
#80000
b0 #
b0 &
b1000 $
