verilog_study/x.v
module x(
    input wire A,B,C,
    output wire F
);
    assign F = A & C;
endmodule

verilog_study/x_tb.v
`timescale 1ns/1ps

module x_tb;
    reg A,B,C;
    wire F;

    x uut(
        .A(A),
        .B(B),
        .C(C),
        .F(F)
    );

    initial begin
        $monitor("Time = %0t | A = %0d,B = %0d,C = %0d,F = %0d",
        $time,A,B,C,F);
        
        A = 0;B = 0;C = 0;
    #10 A = 0;B = 0;C = 1;
    #10 A = 0;B = 1;C = 0;
    #10 A = 0;B = 1;C = 1;
    #10 A = 1;B = 0;C = 0;
    #10 A = 1;B = 0;C = 1;
    #10 A = 1;B = 1;C = 0;
    #10 A = 1;B = 1;C = 1;
    #10
    $finish;
    end
    
    initial begin
        $dumpfile("x.vcd");
        $dumpvars(0,x_tb);
    end
endmodule

verilog_study/x.vcd
$date
	Wed Apr 30 11:07:55 2025
$end
$version
	Icarus Verilog
$end
$timescale
	1ps
$end
$scope module x_tb $end
$var wire 1 ! F $end
$var reg 1 " A $end
$var reg 1 # B $end
$var reg 1 $ C $end
$scope module uut $end
$var wire 1 " A $end
$var wire 1 # B $end
$var wire 1 $ C $end
$var wire 1 ! F $end
$upscope $end
$upscope $end
$enddefinitions $end
$comment Show the parameter values. $end
$dumpall
$end
#0
$dumpvars
0$
0#
0"
0!
$end
#10000
1$
#20000
0$
1#
#30000
1$
#40000
0$
0#
1"
#50000
1!
1$
#60000
0!
0$
1#
#70000
1!
1$
